dj_gcp_rest_auth/__init__.py
dj_gcp_rest_auth/authentication.py
dj_gcp_rest_auth/permissions.py
dj_gcp_rest_auth/serializers.py
dj_gcp_rest_auth/settings.py
dj_gcp_rest_auth/tokens.py
dj_gcp_rest_auth/urls.py
dj_gcp_rest_auth/utils.py
dj_gcp_rest_auth/views.py
dj_gcp_rest_auth-0.6.0.dist-info/METADATA
dj_gcp_rest_auth-0.6.0.dist-info/WHEEL
dj_gcp_rest_auth-0.6.0.dist-info/top_level.txt
dj_gcp_rest_auth-0.6.0.dist-info/RECORD
