Metadata-Version: 2.1
Name: dj-gcp-rest-auth
Version: 0.6.0
Summary: Permissions class for testing a request is coming from an authorized GCP user.
Home-page: https://gitlab.com/pennatus/dj_gcp_rest_auth
Author: Steve Graham
Author-email: stgraham2000@gmail.com
License: MIT license
Keywords: dj_gcp_rest_auth
Platform: UNKNOWN
Classifier: Intended Audience :: Developers
Classifier: License :: OSI Approved :: MIT License
Classifier: Natural Language :: English
Classifier: Programming Language :: Python :: 3.4
Classifier: Programming Language :: Python :: 3.5
Classifier: Programming Language :: Python :: 3.6
Classifier: Programming Language :: Python :: 3.7
Classifier: Programming Language :: Python :: 3.8
Requires-Python: >=3.4
Requires-Dist: google-auth (>=1.18.0)
Requires-Dist: django (>=3.0.7)
Requires-Dist: djangorestframework-simplejwt (>=4.4.0)
Requires-Dist: djangorestframework (==3.11.0)
